django_redis_cache-2.1.3.dist-info/DESCRIPTION.rst
django_redis_cache-2.1.3.dist-info/METADATA
django_redis_cache-2.1.3.dist-info/RECORD
django_redis_cache-2.1.3.dist-info/WHEEL
django_redis_cache-2.1.3.dist-info/metadata.json
django_redis_cache-2.1.3.dist-info/top_level.txt
redis_cache/__init__.py
redis_cache/cache.py
redis_cache/compressors.py
redis_cache/connection.py
redis_cache/constants.py
redis_cache/serializers.py
redis_cache/sharder.py
redis_cache/utils.py
redis_cache/backends/__init__.py
redis_cache/backends/base.py
redis_cache/backends/dummy.py
redis_cache/backends/multiple.py
redis_cache/backends/single.py
